docs/about.md
docs/contribute.md
docs/copyright.md
docs/index.md
docs/input.md
docs/install.md
docs/macros.tex
docs/performance.md
docs/plot.md
docs/plotting.md
docs/requirements.txt
docs/series.md
docs/statistics.md
docs/usage.md
z2n/__init__.py
z2n/file.py
z2n/main.py
z2n/plot.py
z2n/prompt.py
z2n/series.py
z2n/stats.py
z2n_periodogram-2.0.6.dist-info/LICENSE
z2n_periodogram-2.0.6.dist-info/METADATA
z2n_periodogram-2.0.6.dist-info/WHEEL
z2n_periodogram-2.0.6.dist-info/entry_points.txt
z2n_periodogram-2.0.6.dist-info/top_level.txt
z2n_periodogram-2.0.6.dist-info/RECORD
