Metadata-Version: 2.1
Name: z2n-periodogram
Version: 2.0.6
Summary: A package for interative periodograms analysis.
Home-page: https://z2n-periodogram.readthedocs.io
Author: Yohan Alexander
Author-email: yohanfranca@gmail.com
License: MIT
Project-URL: Documentation, https://z2n-periodogram.readthedocs.io
Project-URL: Source, https://github.com/yohanalexander/z2n-periodogram
Platform: UNKNOWN
Classifier: Programming Language :: Python :: 3
Classifier: License :: OSI Approved :: MIT License
Classifier: Operating System :: OS Independent
Classifier: Intended Audience :: Science/Research
Classifier: Topic :: Scientific/Engineering :: Astronomy
Requires-Python: >=3.6.9
Requires-Dist: intel-openmp
Requires-Dist: click
Requires-Dist: pillow
Requires-Dist: click-shell
Requires-Dist: matplotlib
Requires-Dist: termtables
Requires-Dist: colorama
Requires-Dist: astropy
Requires-Dist: psutil
Requires-Dist: numpy
Requires-Dist: numba
Requires-Dist: icc-rt
Requires-Dist: scipy
Requires-Dist: h5py
Requires-Dist: tqdm
Requires-Dist: tbb
Provides-Extra: dev
Requires-Dist: pytest ; extra == 'dev'
Requires-Dist: mkdocs ; extra == 'dev'
Requires-Dist: mkautodoc ; extra == 'dev'
Requires-Dist: markdown-katex ; extra == 'dev'
